struct_frame/__init__.py
struct_frame/__main__.py
struct_frame/base.py
struct_frame/c_gen.py
struct_frame/cpp_gen.py
struct_frame/csharp_gen.py
struct_frame/frame_format.py
struct_frame/frame_formats.proto
struct_frame/frame_parser_c_gen.py
struct_frame/frame_parser_cpp_gen.py
struct_frame/frame_parser_csharp_gen.py
struct_frame/frame_parser_py_gen.py
struct_frame/frame_parser_ts_gen.py
struct_frame/generate.py
struct_frame/generate_boilerplate.py
struct_frame/gql_gen.py
struct_frame/js_gen.py
struct_frame/py_gen.py
struct_frame/ts_gen.py
struct_frame/ts_js_base.py
struct_frame/boilerplate/c/basic_default.h
struct_frame/boilerplate/c/basic_extended.h
struct_frame/boilerplate/c/basic_extended_length.h
struct_frame/boilerplate/c/basic_extended_msg_ids.h
struct_frame/boilerplate/c/basic_extended_multi_system_stream.h
struct_frame/boilerplate/c/basic_minimal.h
struct_frame/boilerplate/c/basic_multi_system_stream.h
struct_frame/boilerplate/c/basic_seq.h
struct_frame/boilerplate/c/basic_sys_comp.h
struct_frame/boilerplate/c/frame_base.h
struct_frame/boilerplate/c/frame_format_config.h
struct_frame/boilerplate/c/frame_parsers.h
struct_frame/boilerplate/c/mavlink_v1_frame.h
struct_frame/boilerplate/c/mavlink_v2_frame.h
struct_frame/boilerplate/c/tiny_default.h
struct_frame/boilerplate/c/tiny_extended.h
struct_frame/boilerplate/c/tiny_extended_length.h
struct_frame/boilerplate/c/tiny_extended_msg_ids.h
struct_frame/boilerplate/c/tiny_extended_multi_system_stream.h
struct_frame/boilerplate/c/tiny_minimal.h
struct_frame/boilerplate/c/tiny_multi_system_stream.h
struct_frame/boilerplate/c/tiny_seq.h
struct_frame/boilerplate/c/tiny_sys_comp.h
struct_frame/boilerplate/c/ubx_frame.h
struct_frame/boilerplate/cpp/BasicDefault.hpp
struct_frame/boilerplate/cpp/BasicExtended.hpp
struct_frame/boilerplate/cpp/BasicExtendedLength.hpp
struct_frame/boilerplate/cpp/BasicExtendedMsgIds.hpp
struct_frame/boilerplate/cpp/BasicExtendedMultiSystemStream.hpp
struct_frame-0.0.51.dist-info/METADATA
struct_frame-0.0.51.dist-info/WHEEL
struct_frame-0.0.51.dist-info/licenses/LICENSE
struct_frame-0.0.51.dist-info/RECORD
